lambdacookie/__init__.py
lambdacookie/caseiter.py
lambdacookie/cookies.py
lambdacookie/version.py
lambdacookie-0.1.0.dist-info/DESCRIPTION.rst
lambdacookie-0.1.0.dist-info/METADATA
lambdacookie-0.1.0.dist-info/RECORD
lambdacookie-0.1.0.dist-info/WHEEL
lambdacookie-0.1.0.dist-info/metadata.json
lambdacookie-0.1.0.dist-info/top_level.txt
