Metadata-Version: 2.0
Name: lambdacookie
Version: 0.1.0
Summary: Provides functions to aid in outputting multiple cookies from
Home-page: https://github.com/Jawshua/aws-lambda-cookies
Author: Joshua Welsh
Author-email: joshua.welsh@performancehorizon.com
License: MIT
Platform: any
